func_validator/__init__.py
func_validator/_func_arg_validator.py
func_validator/validators/__init__.py
func_validator/validators/_core.py
func_validator/validators/collection_arg_validators.py
func_validator/validators/datatype_arg_validators.py
func_validator/validators/dependent_argument_validator.py
func_validator/validators/numeric_arg_validators.py
func_validator/validators/text_arg_validators.py
func_validator-1.3.3.dist-info/licenses/LICENSE
func_validator-1.3.3.dist-info/METADATA
func_validator-1.3.3.dist-info/WHEEL
func_validator-1.3.3.dist-info/top_level.txt
func_validator-1.3.3.dist-info/RECORD
