Metadata-Version: 2.4
Name: func-validator
Version: 1.3.3
Summary: MATLAB-style function argument validation for Python - clean, simple, and reliable.
Author-email: Patrick Boateng <patrickboateng@patrickboateng.tech>
License: MIT License
Project-URL: homepage, https://github.com/patrickboateng/func-validator
Classifier: Development Status :: 2 - Pre-Alpha
Classifier: Intended Audience :: Developers
Classifier: Programming Language :: Python :: 3
Classifier: License :: OSI Approved :: MIT License
Classifier: Natural Language :: English
Classifier: Operating System :: OS Independent
Classifier: Programming Language :: Python :: 3.11
Classifier: Programming Language :: Python :: 3.12
Classifier: Programming Language :: Python :: Implementation :: CPython
Requires-Python: >=3.10
License-File: LICENSE
Dynamic: license-file
